LICENSE.md
MANIFEST.in
README.md
VERSION.txt
requirements.txt
setup.cfg
setup.py
mad_webhooks/__init__.py
mad_webhooks/admin.py
mad_webhooks/application.py
mad_webhooks/apps.py
mad_webhooks/middleware.py
mad_webhooks/models.py
mad_webhooks/settings.py
mad_webhooks/signals.py
mad_webhooks/tasks.py
mad_webhooks/tests.py
mad_webhooks/utils.py
mad_webhooks/webhook.py
mad_webhooks.egg-info/PKG-INFO
mad_webhooks.egg-info/SOURCES.txt
mad_webhooks.egg-info/dependency_links.txt
mad_webhooks.egg-info/requires.txt
mad_webhooks.egg-info/top_level.txt
mad_webhooks/migrations/0001_initial.py
mad_webhooks/migrations/0002_auto_20211021_1910.py
mad_webhooks/migrations/0003_auto_20211129_1024.py
mad_webhooks/migrations/0004_event_log.py
mad_webhooks/migrations/0005_alter_event_log.py
mad_webhooks/migrations/__init__.py