Metadata-Version: 2.1
Name: mad-webhooks
Version: 2.1.0
Summary: A Django app to for webhooks.
Home-page: https://www.madithouse.com/
Author: Haseeb Ur Rehman
Author-email: code@madithouse.com
License: Other/Proprietary License
Classifier: Environment :: Web Environment
Classifier: Framework :: Django
Classifier: Intended Audience :: Developers
Classifier: License :: Other/Proprietary License
Classifier: Operating System :: OS Independent
Classifier: Programming Language :: Python
Classifier: Programming Language :: Python :: 3
Classifier: Programming Language :: Python :: 3.6
Classifier: Topic :: Internet :: WWW/HTTP
Classifier: Topic :: Internet :: WWW/HTTP :: Dynamic Content
Requires-Python: >=3.9
License-File: LICENSE.md
Requires-Dist: django==4.2.6
Requires-Dist: djangorestframework==3.14.0
Requires-Dist: celery==5.3.4
Requires-Dist: django-celery-beat==2.5.0
Requires-Dist: django-filter==23.3
Requires-Dist: django-oauth-toolkit==2.3.0
